{
  "quizTitle": "Assamese - 1",
  "topicTitle": "Assamese Script",
  "disabledTypes": ["map_name", "map_flag", "wordgrid", "spell", "fragments"],
  "items": [
    { "promptText": "অ", "answerText": "a/o", "tags": { "type": "vowel" } },
    { "promptText": "আ", "answerText": "aa/ā", "tags": { "type": "vowel" } },
    { "promptText": "ই", "answerText": "i", "tags": { "type": "vowel" } },
    { "promptText": "ঈ", "answerText": "ee/ī", "tags": { "type": "vowel" } },
    { "promptText": "উ", "answerText": "u", "tags": { "type": "vowel" } },
    { "promptText": "ঊ", "answerText": "oo/ū", "tags": { "type": "vowel" } },
    { "promptText": "ঋ", "answerText": "ri/ṛ", "tags": { "type": "vowel" } },
    { "promptText": "এ", "answerText": "e", "tags": { "type": "vowel" } },
    { "promptText": "ঐ", "answerText": "oi", "tags": { "type": "vowel" } },
    { "promptText": "ও", "answerText": "o", "tags": { "type": "vowel" } },
    { "promptText": "ঔ", "answerText": "ou", "tags": { "type": "vowel" } },
    { "promptText": "ক", "answerText": "ka/ko", "tags": { "type": "consonant" } },
    { "promptText": "খ", "answerText": "kha/kho", "tags": { "type": "consonant" } },
    { "promptText": "গ", "answerText": "ga/go", "tags": { "type": "consonant" } },
    { "promptText": "ঘ", "answerText": "gha/gho", "tags": { "type": "consonant" } },
    { "promptText": "ঙ", "answerText": "nga/ngo", "tags": { "type": "consonant" } },
    { "promptText": "চ", "answerText": "sa/so", "tags": { "type": "consonant" } },
    { "promptText": "ছ", "answerText": "sha/sho", "tags": { "type": "consonant" } },
    { "promptText": "জ", "answerText": "za/zo", "tags": { "type": "consonant" } },
    { "promptText": "ঝ", "answerText": "zha/zho", "tags": { "type": "consonant" } },
    { "promptText": "ঞ", "answerText": "nya/nyo", "tags": { "type": "consonant" } },
    { "promptText": "ট", "answerText": "ṭa/ṭo", "tags": { "type": "consonant" } },
    { "promptText": "ঠ", "answerText": "ṭha/ṭho", "tags": { "type": "consonant" } },
    { "promptText": "ড", "answerText": "ḍa/ḍo", "tags": { "type": "consonant" } },
    { "promptText": "ঢ", "answerText": "ḍha/ḍho", "tags": { "type": "consonant" } },
    { "promptText": "ণ", "answerText": "ṇa/ṇo", "tags": { "type": "consonant" } },
    { "promptText": "ত", "answerText": "ta/to", "tags": { "type": "consonant" } },
    { "promptText": "থ", "answerText": "tha/tho", "tags": { "type": "consonant" } },
    { "promptText": "দ", "answerText": "da/do", "tags": { "type": "consonant" } },
    { "promptText": "ধ", "answerText": "dha/dho", "tags": { "type": "consonant" } },
    { "promptText": "ন", "answerText": "na/no", "tags": { "type": "consonant" } },
    { "promptText": "প", "answerText": "pa/po", "tags": { "type": "consonant" } },
    { "promptText": "ফ", "answerText": "pha/pho", "tags": { "type": "consonant" } },
    { "promptText": "ব", "answerText": "ba/bo", "tags": { "type": "consonant" } },
    { "promptText": "ভ", "answerText": "bha/bho", "tags": { "type": "consonant" } },
    { "promptText": "ম", "answerText": "ma/mo", "tags": { "type": "consonant" } },
    { "promptText": "য", "answerText": "za/zo (antostho)", "tags": { "type": "consonant" } },
    { "promptText": "ৰ", "answerText": "ra/ro", "tags": { "type": "consonant" } },
    { "promptText": "ল", "answerText": "la/lo", "tags": { "type": "consonant" } },
    { "promptText": "ৱ", "answerText": "wa/wo", "tags": { "type": "consonant" } },
    { "promptText": "শ", "answerText": "sha/sho", "tags": { "type": "consonant" } },
    { "promptText": "ষ", "answerText": "kha/kho (ksha)", "tags": { "type": "consonant" } },
    { "promptText": "স", "answerText": "ha/ho", "tags": { "type": "consonant" } },
    { "promptText": "হ", "answerText": "ha/ho", "tags": { "type": "consonant" } },
    { "promptText": "ড়", "answerText": "ṛa/ṛo", "tags": { "type": "consonant" } },
    { "promptText": "ঢ়", "answerText": "ṛha/ṛho", "tags": { "type": "consonant" } },
    { "promptText": "য়", "answerText": "ya/yo", "tags": { "type": "consonant" } },
    { "promptText": "ং", "answerText": "anusvara", "tags": { "type": "sign" } },
    { "promptText": "ঃ", "answerText": "visarga", "tags": { "type": "sign" } },
    { "promptText": "ঁ", "answerText": "chandrabindu", "tags": { "type": "sign" } }
  ]
}
